<?xml version="1.0" encoding="utf-8"?>
<resources>
    <dimen name="cc_pay_font_size_24">36.00px</dimen>

    <dimen name="cc_pay_font_size_30">45.00px</dimen>

    <dimen name="cc_pay_font_size_32">48.00px</dimen>

    <dimen name="cc_pay_font_size_40">60.00px</dimen>

    
    <dimen name="cc_pay_margin_5">7.50px</dimen>

    <dimen name="cc_pay_margin_10">15.00px</dimen>

    <dimen name="cc_pay_margin_20">30.00px</dimen>

    <dimen name="cc_pay_margin_22">33.00px</dimen>

    <dimen name="cc_pay_margin_32">48.00px</dimen>

    <dimen name="cc_pay_margin_30">45.00px</dimen>

    <dimen name="cc_pay_margin_40">60.00px</dimen>

    <dimen name="cc_pay_margin_45">67.50px</dimen>

    <dimen name="cc_pay_margin_50">75.00px</dimen>

    <dimen name="cc_pay_margin_55">82.50px</dimen>

    <dimen name="cc_pay_margin_54">81.00px</dimen>

    <dimen name="cc_pay_margin_60">90.00px</dimen>

    <dimen name="cc_pay_margin_80">120.00px</dimen>

    <dimen name="cc_pay_margin_100">150.00px</dimen>

    <dimen name="cc_pay_margin_180">270.00px</dimen>

    
    <dimen name="cc_pay_width_130">195.00px</dimen>

    <dimen name="cc_pay_width_150">225.00px</dimen>

    <dimen name="cc_pay_width_250">375.00px</dimen>

    <dimen name="cc_pay_height_80">120.00px</dimen>    

    <dimen name="cc_pay_height_90">135.00px</dimen>    

    <dimen name="cc_pay_height_180">270.00px</dimen>

    <dimen name="cc_pay_height_128">192.00px</dimen>    

    <dimen name="cc_pay_height_130">195.00px</dimen>    

    <dimen name="cc_pay_height_100">150.00px</dimen>    

</resources>
