{"skeleton":{"hash":"ajzp86SekuofghbNA0syxyEVt4U","spine":"2.1.27","width":200,"height":200,"images":""},"bones":[{"name":"root"}],"slots":[{"name":"battleEffect/effect_bruise","bone":"root","attachment":"z6/z6_sw_stand_8"}],"skins":{"default":{"battleEffect/effect_bruise":{"z6/z6_sw_attack_1":{"width":200,"height":200},"z6/z6_sw_attack_2":{"width":200,"height":200},"z6/z6_sw_attack_3":{"width":200,"height":200},"z6/z6_sw_attack_4":{"width":200,"height":200},"z6/z6_sw_attack_5":{"width":200,"height":200},"z6/z6_sw_hit_1":{"width":200,"height":200},"z6/z6_sw_hit_2":{"width":200,"height":200},"z6/z6_sw_hit_3":{"width":200,"height":200},"z6/z6_sw_hit_4":{"width":200,"height":200},"z6/z6_sw_run_1":{"width":200,"height":200},"z6/z6_sw_run_2":{"width":200,"height":200},"z6/z6_sw_run_3":{"width":200,"height":200},"z6/z6_sw_run_4":{"width":200,"height":200},"z6/z6_sw_run_5":{"width":200,"height":200},"z6/z6_sw_run_6":{"width":200,"height":200},"z6/z6_sw_run_7":{"width":200,"height":200},"z6/z6_sw_run_8":{"width":200,"height":200},"z6/z6_sw_stand_1":{"width":200,"height":200},"z6/z6_sw_stand_2":{"width":200,"height":200},"z6/z6_sw_stand_3":{"width":200,"height":200},"z6/z6_sw_stand_4":{"width":200,"height":200},"z6/z6_sw_stand_5":{"width":200,"height":200},"z6/z6_sw_stand_6":{"width":200,"height":200},"z6/z6_sw_stand_7":{"width":200,"height":200},"z6/z6_sw_stand_8":{"width":200,"height":200}}}},"animations":{"sw_attack":{"slots":{"battleEffect/effect_bruise":{"attachment":[{"time":0,"name":"z6/z6_sw_attack_1"},{"time":0.1,"name":"z6/z6_sw_attack_2"},{"time":0.2,"name":"z6/z6_sw_attack_3"},{"time":0.3666,"name":"z6/z6_sw_attack_4"},{"time":0.5333,"name":"z6/z6_sw_attack_5"}]}},"bones":{"root":{"translate":[{"time":0,"x":0,"y":0}]}}},"sw_hit":{"slots":{"battleEffect/effect_bruise":{"attachment":[{"time":0,"name":"z6/z6_sw_hit_1"},{"time":0.0666,"name":"z6/z6_sw_hit_2"},{"time":0.1666,"name":"z6/z6_sw_hit_3"},{"time":0.3,"name":"z6/z6_sw_hit_4"},{"time":0.4333,"name":"z6/z6_sw_stand_1"}]}}},"sw_run":{"slots":{"battleEffect/effect_bruise":{"attachment":[{"time":0,"name":"z6/z6_sw_run_1"},{"time":0.0666,"name":"z6/z6_sw_run_2"},{"time":0.1666,"name":"z6/z6_sw_run_3"},{"time":0.2666,"name":"z6/z6_sw_run_4"},{"time":0.3666,"name":"z6/z6_sw_run_5"},{"time":0.4333,"name":"z6/z6_sw_run_6"},{"time":0.5,"name":"z6/z6_sw_run_7"},{"time":0.5666,"name":"z6/z6_sw_run_8"}]}},"bones":{"root":{"translate":[{"time":0,"x":0,"y":0}]}}},"sw_stand":{"slots":{"battleEffect/effect_bruise":{"attachment":[{"time":0,"name":"z6/z6_sw_stand_1"},{"time":0.1,"name":"z6/z6_sw_stand_2"},{"time":0.2,"name":"z6/z6_sw_stand_3"},{"time":0.3,"name":"z6/z6_sw_stand_4"},{"time":0.4,"name":"z6/z6_sw_stand_5"},{"time":0.5,"name":"z6/z6_sw_stand_6"},{"time":0.6,"name":"z6/z6_sw_stand_7"},{"time":0.7,"name":"z6/z6_sw_stand_8"},{"time":0.8,"name":"z6/z6_sw_stand_1"}]}}}}}